[
  {
    "lot_number": "24560",
    "brand": "Daihatsu",
    "model": "COPEN",
    "auction_date": "05.01.2026",
    "year": 2015,
    "mileage": 6000,
    "price": 1083000,
    "lot_url": "https://japantransit.ru/auctions/?id=8Sx3QgCdi57roOA",
    "images": [
      "https://7.ajes.com/imgs/4jbCAJeJ7k2TjciTumxcCpvQC18TZHFetML2s7hDPldRnaRby0hAwA&h=50",
      "https://7.ajes.com/imgs/4jbCAJeJ7k2TjciTumxcCpvQC18TZHFetML2s7hDPldRnaDXcljR4k&h=50"
    ]
  },
  {
    "lot_number": "24578",
    "brand": "Mazda",
    "model": "FLAIR",
    "auction_date": "05.01.2026",
    "year": 2020,
    "mileage": 28000,
    "price": 597000,
    "lot_url": "https://japantransit.ru/auctions/?id=8SC2Srv4drrKIaj",
    "images": [
      "https://7.ajes.com/imgs/4jbCAJeJ7k2TjciTumxcCpvQC18TZHFetML2s7gei7H4W1p6x8NkCF&h=50",
      "https://7.ajes.com/imgs/4jbCAJeJ7k2TjciTumxcCpvQC18TZHFetML2s7gei7H4W1bRbjPB0p&h=50"
    ]
  },
  {
    "lot_number": "24543",
    "brand": "Honda",
    "model": "N BOX",
    "auction_date": "05.01.2026",
    "year": 2021,
    "mileage": 34000,
    "price": 942000,
    "lot_url": "https://japantransit.ru/auctions/?id=8Si6JJXHvW5vsLp",
    "images": [
      "https://7.ajes.com/imgs/4jbCAJeJ7k2TjciTumxcCpvQC18TZHFetML2s7fwwuqDex9H96d2lJ&h=50",
      "https://7.ajes.com/imgs/4jbCAJeJ7k2TjciTumxcCpvQC18TZHFetML2s7fwwuqDewVsMhfhSt&h=50"
    ]
  },
  {
    "lot_number": "1007",
    "brand": "Mazda",
    "model": "CX-30",
    "auction_date": "05.01.2026",
    "year": 2020,
    "mileage": 43000,
    "price": 1718000,
    "lot_url": "https://japantransit.ru/auctions/?id=3gihkG1rdmMG0o",
    "images": [
      "https://7.ajes.com/imgs/hJ34iW9UhPGTL7QPMRj40KdbuR6w4wbE5yXEV7bJKZGYI4iW&h=50",
      "https://7.ajes.com/imgs/hJ34iW9UhPGTL7QPMRj40KdbuR6w4wbE5yXEVi64Z550L0eN&h=50"
    ]
  },
  {
    "lot_number": "24559",
    "brand": "Nissan",
    "model": "DAYZ",
    "auction_date": "05.01.2026",
    "year": 2021,
    "mileage": 56000,
    "price": 641000,
    "lot_url": "https://japantransit.ru/auctions/?id=8SqHwAA4zdQADDQ",
    "images": [
      "https://7.ajes.com/imgs/4jbCAJeJ7k2TjciTumxcCpvQC18TZHFetML2s7gW4IY5jslH4HwVHa&h=50",
      "https://7.ajes.com/imgs/4jbCAJeJ7k2TjciTumxcCpvQC18TZHFetML2s7gW4IY5js9sHTzcdU&h=50"
    ]
  },
  {
    "lot_number": "13023",
    "brand": "Nissan",
    "model": "X-TRAIL",
    "auction_date": "05.01.2026",
    "year": 2021,
    "mileage": 42000,
    "price": 1849000,
    "lot_url": "https://japantransit.ru/auctions/?id=5ltOvnzkixlbmKM",
    "images": [
      "https://7.ajes.com/imgs/4jbCAJeJ7k2TjciTumxcCpvQC18TZHFetML2s7hDPlevO6ee2m4juT&h=50",
      "https://7.ajes.com/imgs/4jbCAJeJ7k2TjciTumxcCpvQC18TZHFetML2s7hDPlevO61ZFy6A2D&h=50"
    ]
  },
  {
    "lot_number": "13019",
    "brand": "Nissan",
    "model": "SERENA",
    "auction_date": "05.01.2026",
    "year": 2025,
    "mileage": 1000,
    "price": 2490000,
    "lot_url": "https://japantransit.ru/auctions/?id=5lqDQxyfr8dfZap",
    "images": [
      "https://7.ajes.com/imgs/4jbCAJeJ7k2TjciTumxcCpvQC18TZHFetML2s7fwwuqEOQmYfj6apj&h=50",
      "https://7.ajes.com/imgs/4jbCAJeJ7k2TjciTumxcCpvQC18TZHFetML2s7fwwuqEOQ0JTv8qW4&h=50"
    ]
  },
  {
    "lot_number": "24551",
    "brand": "Suzuki",
    "model": "JIMNY",
    "auction_date": "05.01.2026",
    "year": 2023,
    "mileage": 13000,
    "price": 1303000,
    "lot_url": "https://japantransit.ru/auctions/?id=8Sn5LUQxrjpOM89",
    "images": [
      "https://7.ajes.com/imgs/4jbCAJeJ7k2TjciTumxcCpvQC18TZHFetML2s7ilAXuB7mSTlSlEuu&h=50",
      "https://7.ajes.com/imgs/4jbCAJeJ7k2TjciTumxcCpvQC18TZHFetML2s7ilAXuB7mFF15nV2e&h=50"
    ]
  },
  {
    "lot_number": "60216",
    "brand": "Honda",
    "model": "VEZEL",
    "auction_date": "05.01.2026",
    "year": 2019,
    "mileage": 72000,
    "price": 1613000,
    "lot_url": "https://japantransit.ru/auctions/?id=mPCFj7XsMPR9cf9",
    "images": [
      "https://7.ajes.com/imgs/60F7XdoZnLBkGYc0FeSLjzJlujgzJkV8MgpEjnHaYftC1mSdhwDRz3ouE&h=50",
      "https://7.ajes.com/imgs/60F7XdoZnLBkGYc0FeSLjzJlujgzJkV8MgpEjnHaYftC1mSdhwE49HNd8&h=50"
    ]
  },
  {
    "lot_number": "24516",
    "brand": "Suzuki",
    "model": "SPACIA GEAR",
    "auction_date": "05.01.2026",
    "year": 2024,
    "price": 809000,
    "lot_url": "https://japantransit.ru/auctions/?id=8S2MlI0RWl935Td",
    "images": [
      "https://7.ajes.com/imgs/4jbCAJeJ7k2TjciTumxcCpvQC18TZHFetML2s7lSr3Prq7qjw8R0pQ&h=50",
      "https://7.ajes.com/imgs/4jbCAJeJ7k2TjciTumxcCpvQC18TZHFetML2s7lSr3Prq7d6ajTpWA&h=50"
    ]
  },
  {
    "lot_number": "24574",
    "brand": "Honda",
    "model": "S660",
    "auction_date": "05.01.2026",
    "year": 2018,
    "mileage": 49000,
    "price": 1245000,
    "lot_url": "https://japantransit.ru/auctions/?id=8SAdv7Di0uemMoX",
    "images": [
      "https://7.ajes.com/imgs/4jbCAJeJ7k2TjciTumxcCpvQC18TZHFetML2s6ysFQe4KPhQ1oSUup&h=50",
      "https://7.ajes.com/imgs/4jbCAJeJ7k2TjciTumxcCpvQC18TZHFetML2s6ysFQe4KP5BEAVb20&h=50"
    ]
  },
  {
    "lot_number": "10026",
    "brand": "Toyota",
    "model": "C-HR",
    "auction_date": "05.01.2026",
    "year": 2018,
    "mileage": 57000,
    "price": 1563000,
    "lot_url": "https://japantransit.ru/auctions/?id=70TRW9VV7R72CoO",
    "images": [
      "https://7.ajes.com/imgs/4jbCAJeJ7k2TjciTumxcCpvQC18TZHFetML2s7hDPle3tlt8mIoBVE&h=50",
      "https://7.ajes.com/imgs/4jbCAJeJ7k2TjciTumxcCpvQC18TZHFetML2s7hDPle3tlfT1UqSso&h=50"
    ]
  },
  {
    "lot_number": "24572",
    "brand": "Honda",
    "model": "S660",
    "auction_date": "05.01.2026",
    "year": 2016,
    "mileage": 45000,
    "price": 1233000,
    "lot_url": "https://japantransit.ru/auctions/?id=8SzjjrcpCvCFOwh",
    "images": [
      "https://7.ajes.com/imgs/4jbCAJeJ7k2TjciTumxcCpvQC18TZHFetML2s6zarstOr5WUP1PlJs&h=50",
      "https://7.ajes.com/imgs/4jbCAJeJ7k2TjciTumxcCpvQC18TZHFetML2s6zarstOr5JGtcRCgc&h=50"
    ]
  },
  {
    "lot_number": "10018",
    "brand": "Lexus",
    "model": "RX",
    "auction_date": "05.01.2026",
    "year": 2016,
    "mileage": 65000,
    "price": 2437000,
    "lot_url": "https://japantransit.ru/auctions/?id=70OSTY46btKIj46",
    "images": [
      "https://7.ajes.com/imgs/4jbCAJeJ7k2TjciTumxcCpvQC18TZHFetML2s6zarstISZDWUJgQ2V&h=50",
      "https://7.ajes.com/imgs/4jbCAJeJ7k2TjciTumxcCpvQC18TZHFetML2s6zarstISZqIyVj7yF&h=50"
    ]
  },
  {
    "lot_number": "14501",
    "brand": "Toyota",
    "model": "ROOMY",
    "auction_date": "05.01.2026",
    "year": 2021,
    "mileage": 36000,
    "price": 1023000,
    "lot_url": "https://japantransit.ru/auctions/?id=5w7FkdKKZdjZwTg",
    "images": [
      "https://7.ajes.com/imgs/4jbCAJeJ7k2TjciTumxcCpvQC18TZHFetML2s7gW4IXBLScIXFOiEI&h=50",
      "https://7.ajes.com/imgs/4jbCAJeJ7k2TjciTumxcCpvQC18TZHFetML2s7gW4IXBLRZuBRQzbs&h=50"
    ]
  },
  {
    "lot_number": "10027",
    "brand": "Suzuki",
    "model": "SWIFT",
    "auction_date": "05.01.2026",
    "year": 2019,
    "mileage": 57000,
    "price": 1332000,
    "lot_url": "https://japantransit.ru/auctions/?id=70Uk2YEmnloS7l0",
    "images": [
      "https://7.ajes.com/imgs/4jbCAJeJ7k2TjciTumxcCpvQC18TZHFetML2s7hDPle4gv6fVkkGsr&h=50",
      "https://7.ajes.com/imgs/4jbCAJeJ7k2TjciTumxcCpvQC18TZHFetML2s7hDPle4guS2zwmWZb&h=50"
    ]
  },
  {
    "lot_number": "24511",
    "brand": "Suzuki",
    "model": "ALTO",
    "auction_date": "05.01.2026",
    "year": 2015,
    "mileage": 24000,
    "price": 647000,
    "lot_url": "https://japantransit.ru/auctions/?id=8RZvSxzFBTBNFbw",
    "images": [
      "https://7.ajes.com/imgs/4jbCAJeJ7k2TjciTumxcCpvQC18TZHFetML2s6zarsupHmRp4LQMAB&h=50",
      "https://7.ajes.com/imgs/4jbCAJeJ7k2TjciTumxcCpvQC18TZHFetML2s6zarsupHmEaHXT48l&h=50"
    ]
  },
  {
    "lot_number": "13505",
    "brand": "Nissan",
    "model": "X-TRAIL",
    "auction_date": "05.01.2026",
    "year": 2020,
    "mileage": 75000,
    "price": 1814000,
    "lot_url": "https://japantransit.ru/auctions/?id=5g5WXWSkLkHCuot",
    "images": [
      "https://7.ajes.com/imgs/4jbCAJeJ7k2TjciTumxcCpvQC18TZHFetML2s7lSr3Qk8NRQ3lubUn&h=50",
      "https://7.ajes.com/imgs/4jbCAJeJ7k2TjciTumxcCpvQC18TZHFetML2s7lSr3Qk8NEBGxwsr8&h=50"
    ]
  },
  {
    "lot_number": "13020",
    "brand": "Toyota",
    "model": "SUCCEED",
    "auction_date": "05.01.2026",
    "year": 2018,
    "mileage": 53000,
    "price": 1147000,
    "lot_url": "https://japantransit.ru/auctions/?id=5lwZadAp0Xt7Kl0",
    "images": [
      "https://7.ajes.com/imgs/4jbCAJeJ7k2TjciTumxcCpvQC18TZHFetML2s7gei7H3lHaOpTVbz6&h=50",
      "https://7.ajes.com/imgs/4jbCAJeJ7k2TjciTumxcCpvQC18TZHFetML2s7gei7H3lGXA56Xs6P&h=50"
    ]
  },
  {
    "lot_number": "24501",
    "brand": "Honda",
    "model": "N VAN",
    "auction_date": "05.01.2026",
    "year": 2022,
    "mileage": 45000,
    "price": 1126000,
    "lot_url": "https://japantransit.ru/auctions/?id=8SQwT9r8J6aQah0",
    "images": [
      "https://7.ajes.com/imgs/4jbCAJeJ7k2TjciTumxcCpvQC18TZHFetML2s7fwwursLC8FpR6LJ7&h=50",
      "https://7.ajes.com/imgs/4jbCAJeJ7k2TjciTumxcCpvQC18TZHFetML2s7fwwursLBUr5493fQ&h=50"
    ]
  }
]